npap/__init__.py
npap-0.0.1.dist-info/licenses/LICENSE
npap-0.0.1.dist-info/METADATA
npap-0.0.1.dist-info/WHEEL
npap-0.0.1.dist-info/top_level.txt
npap-0.0.1.dist-info/RECORD
