Metadata-Version: 2.4
Name: npap
Version: 0.0.1
Summary: Network Partitioning & Aggregation Package
Author: Marco Antonio Arnaiz Montero
License-File: LICENSE
Dynamic: license-file
